[
  {
    "event": "At the December draw",
    "items": [
      {
        "name": "Spain",
        "value": 18.2
      },
      {
        "name": "England",
        "value": 15.4
      },
      {
        "name": "France",
        "value": 11.8
      },
      {
        "name": "Brazil",
        "value": 11.1
      },
      {
        "name": "Argentina",
        "value": 10
      },
      {
        "name": "Portugal",
        "value": 9.1
      },
      {
        "name": "Germany",
        "value": 6.7
      },
      {
        "name": "Netherlands",
        "value": 4.8
      },
      {
        "name": "Norway",
        "value": 3.4
      },
      {
        "name": "Belgium",
        "value": 2.8
      }
    ]
  },
  {
    "event": "Jun 11 · per ESPN/DraftKings",
    "items": [
      {
        "name": "Spain",
        "value": 18.2
      },
      {
        "name": "France",
        "value": 17.4
      },
      {
        "name": "England",
        "value": 14.3
      },
      {
        "name": "Portugal",
        "value": 11.1
      },
      {
        "name": "Brazil",
        "value": 10.5
      },
      {
        "name": "Argentina",
        "value": 10.5
      },
      {
        "name": "Germany",
        "value": 6.7
      },
      {
        "name": "Netherlands",
        "value": 4.8
      },
      {
        "name": "Norway",
        "value": 3.4
      },
      {
        "name": "Belgium",
        "value": 2.8
      }
    ]
  },
  {
    "event": "Jun 11",
    "items": [
      {
        "name": "Spain",
        "value": 15
      },
      {
        "name": "France",
        "value": 14.7
      },
      {
        "name": "England",
        "value": 10
      },
      {
        "name": "Portugal",
        "value": 9.7
      },
      {
        "name": "Brazil",
        "value": 8.1
      },
      {
        "name": "Argentina",
        "value": 7.9
      },
      {
        "name": "Germany",
        "value": 5.5
      },
      {
        "name": "Netherlands",
        "value": 4.1
      },
      {
        "name": "Norway",
        "value": 2.9
      },
      {
        "name": "Belgium",
        "value": 2.2
      }
    ]
  },
  {
    "event": "Jun 12",
    "items": [
      {
        "name": "Spain",
        "value": 15
      },
      {
        "name": "France",
        "value": 14.7
      },
      {
        "name": "England",
        "value": 10
      },
      {
        "name": "Portugal",
        "value": 9.7
      },
      {
        "name": "Brazil",
        "value": 8.1
      },
      {
        "name": "Argentina",
        "value": 7.9
      },
      {
        "name": "Germany",
        "value": 5.5
      },
      {
        "name": "Netherlands",
        "value": 4.1
      },
      {
        "name": "Norway",
        "value": 2.9
      },
      {
        "name": "Belgium",
        "value": 2.2
      }
    ]
  },
  {
    "event": "Jun 12",
    "items": [
      {
        "name": "Spain",
        "value": 15
      },
      {
        "name": "France",
        "value": 14.7
      },
      {
        "name": "England",
        "value": 10
      },
      {
        "name": "Portugal",
        "value": 9.7
      },
      {
        "name": "Brazil",
        "value": 8.1
      },
      {
        "name": "Argentina",
        "value": 7.9
      },
      {
        "name": "Germany",
        "value": 5.5
      },
      {
        "name": "Netherlands",
        "value": 4.1
      },
      {
        "name": "Norway",
        "value": 2.9
      },
      {
        "name": "Belgium",
        "value": 2.2
      }
    ]
  },
  {
    "event": "Jun 13",
    "items": [
      {
        "name": "Spain",
        "value": 15
      },
      {
        "name": "France",
        "value": 14.6
      },
      {
        "name": "England",
        "value": 10
      },
      {
        "name": "Portugal",
        "value": 9.4
      },
      {
        "name": "Brazil",
        "value": 8
      },
      {
        "name": "Argentina",
        "value": 7.9
      },
      {
        "name": "Germany",
        "value": 5.5
      },
      {
        "name": "Netherlands",
        "value": 4.3
      },
      {
        "name": "Norway",
        "value": 2.9
      },
      {
        "name": "Belgium",
        "value": 2.2
      }
    ]
  },
  {
    "event": "Jun 14",
    "items": [
      {
        "name": "France",
        "value": 15.1
      },
      {
        "name": "Spain",
        "value": 15.1
      },
      {
        "name": "England",
        "value": 10.1
      },
      {
        "name": "Portugal",
        "value": 9.2
      },
      {
        "name": "Argentina",
        "value": 7.9
      },
      {
        "name": "Brazil",
        "value": 6.9
      },
      {
        "name": "Germany",
        "value": 5.5
      },
      {
        "name": "Netherlands",
        "value": 4.6
      },
      {
        "name": "Norway",
        "value": 2.4
      },
      {
        "name": "Morocco",
        "value": 2.4
      }
    ]
  }
]
